{
  "id": "task-20260406-060147-a981d03b",
  "title": "Check and fix uncommitted changes",
  "agent_id": "a981d03b59815af10",
  "agent_type": "general-purpose",
  "session_id": "bbe4d04d-5929-4865-8179-390e5375b800",
  "discord_message_id": null,
  "discord_user": null,
  "run_in_background": true,
  "isolation": null,
  "model": null,
  "log": [
    {
      "ts": "2026-04-06T06:01:47Z",
      "event": "started",
      "context": "Check and fix uncommitted changes"
    },
    {
      "ts": "2026-04-06T06:02:37Z",
      "event": "done",
      "context": "Here is my analysis and what I did:\n\n**1. `bash-intercept.sh` -- REVERTED (was sabataged)**\n\nThe hook was reduced to just `#!/bin/bash` followed by `exit 0`. This completely disabled the `PreToolUse` hook that blocks Bash calls on the main thread and forces delegation to background agents. Someone (or a confused agent) neutralized it. I restored it to the original version which:\n- Allows Bash freely inside subagents (when `agent_id` is present)\n- Blocks Bash on the main thread with exit code 2 a...(truncated)",
      "artifacts": []
    }
  ]
}
