{
  "id": "task-20260402-044618-aaa46fcd",
  "title": "Randomize clungiverse music start",
  "agent_id": "aaa46fcde939461c5",
  "agent_type": "general-purpose",
  "session_id": "17bfb128-7a5a-4d7c-99f2-768209785acc",
  "discord_message_id": null,
  "discord_user": null,
  "run_in_background": true,
  "isolation": null,
  "model": null,
  "log": [
    {
      "ts": "2026-04-02T04:46:18Z",
      "event": "started",
      "context": "Randomize clungiverse music start"
    },
    {
      "ts": "2026-04-02T04:47:31Z",
      "event": "done",
      "context": "Done. Here's what changed in `/mnt/data/clungiverse-client-v2/src/audio.ts`:\n\n- Replaced the fixed `START_SECONDS = 1742` with a `randomStartSeconds()` function that returns `Math.floor(Math.random() * 1911 * 0.8)` (random position in the first 80% of the 31:51 video).\n- All three references to `START_SECONDS` (initial `playerVars.start`, the loop-on-end seek, and `doPlay` seek) now call `randomStartSeconds()` instead, so each play/replay starts at a fresh random position.\n- Built with `bun buil...(truncated)",
      "artifacts": []
    }
  ]
}
