{
  "id": "task-20260402-161224-a15ad8ac",
  "title": "handle [heartbeat] trigger per TRIGGERS.md",
  "agent_id": "a15ad8acb23b72867",
  "agent_type": "general-purpose",
  "session_id": "6e457a76-d639-4c73-8930-ab74edfc55cb",
  "discord_message_id": "omni_32csxkgr",
  "discord_user": null,
  "run_in_background": true,
  "isolation": null,
  "model": null,
  "log": [
    {
      "ts": "2026-04-02T16:12:24Z",
      "event": "started",
      "context": "handle [heartbeat] trigger per TRIGGERS.md"
    },
    {
      "ts": "2026-04-02T16:19:57Z",
      "event": "done",
      "context": "",
      "artifacts": []
    }
  ]
}
