{
  "id": "task-20260324-180739-a21d5ad4",
  "title": "Audit stalled tasks and close resolved ones",
  "agent_id": "a21d5ad4d731dc5ca",
  "agent_type": "general-purpose",
  "session_id": "bb9407c6-0d39-400c-af71-7c6765df2c69",
  "discord_message_id": null,
  "discord_user": null,
  "run_in_background": true,
  "isolation": null,
  "model": null,
  "log": [
    {
      "ts": "2026-03-24T18:07:39Z",
      "event": "started",
      "context": "Audit stalled tasks and close resolved ones"
    },
    {
      "ts": "2026-03-24T18:10:10Z",
      "event": "done",
      "message": "Audit complete. 7 tasks marked done, 2 marked stale (probationary verdict enforcement, landing page dashboard). Committed and pushed."
    }
  ]
}