{
  "id": "task-20260402-044651-adf42ed8",
  "title": "Debug uwu emoji image issue",
  "agent_id": "adf42ed8ebd861c28",
  "agent_type": "general-purpose",
  "session_id": "17bfb128-7a5a-4d7c-99f2-768209785acc",
  "discord_message_id": null,
  "discord_user": null,
  "run_in_background": true,
  "isolation": null,
  "model": null,
  "log": [
    {
      "ts": "2026-04-02T04:46:51Z",
      "event": "started",
      "context": "Debug uwu emoji image issue"
    },
    {
      "ts": "2026-04-02T04:49:13Z",
      "event": "done",
      "context": "Everything is working. Here's a summary of what was done:\n\n**Root causes found and fixed:**\n\n1. **Bad URL in DB**: The `custom_emojis` table had `url` set to `https://emoji.gg/emoji/663176-uwu` (a webpage, not an image URL). This was uploaded before the local-fetch fix was deployed. Updated to `/api/emojis/img/uwu.png`.\n\n2. **Route ordering bug in `/mnt/data/clungcord/packages/server/src/index.ts`**: The `/api/emojis/img/` static file handler (line 253) was placed *after* the general `/api/` han...(truncated)",
      "artifacts": []
    }
  ]
}
