{
  "id": "task-20260407-233817-a34270fc",
  "title": "Heartbeat check",
  "agent_id": "a34270fc62992a431",
  "agent_type": "general-purpose",
  "session_id": "38879609-c8bd-47f5-af26-6210d2de543c",
  "discord_message_id": null,
  "discord_user": null,
  "run_in_background": true,
  "isolation": null,
  "model": null,
  "log": [
    {
      "ts": "2026-04-07T23:38:17Z",
      "event": "started",
      "context": "Heartbeat check"
    },
    {
      "ts": "2026-04-07T23:39:28Z",
      "event": "done",
      "context": "All clean. No stale tasks, no failed services, no actionable issues, no timeline candidates. Nothing to post. Heartbeat complete.",
      "artifacts": []
    }
  ]
}
