{
  "id": "task-20260401-185906-ad192139",
  "title": "Clungiverse v2 Phase 2",
  "agent_id": "ad192139701eaa0b6",
  "agent_type": "general-purpose",
  "session_id": "17bfb128-7a5a-4d7c-99f2-768209785acc",
  "discord_message_id": null,
  "discord_user": null,
  "run_in_background": true,
  "isolation": null,
  "model": null,
  "log": [
    {
      "ts": "2026-04-01T18:59:06Z",
      "event": "started",
      "context": "Clungiverse v2 Phase 2"
    },
    {
      "ts": "2026-04-01T19:05:13Z",
      "event": "done",
      "context": "All four tasks are complete. Here is the summary:\n\n---\n\n## Completed: Phase 2 Clungiverse v2 PixiJS Migration\n\n### Files created/modified:\n\n**New file:**\n- `/mnt/data/clungiverse-client-v2/src/renderer/sprites.ts` (140 lines) -- PixiJS texture management for avatars and mob sprites\n\n**Rewritten files:**\n- `/mnt/data/clungiverse-client-v2/src/renderer/entity-renderer.ts` (513 lines) -- Full entity rendering\n- `/mnt/data/clungiverse-client-v2/src/renderer/particle-renderer.ts` (264 lines) -- Parti...(truncated)",
      "artifacts": []
    }
  ]
}
