{
  "id": "task-20260407-051404-a71621bd",
  "title": "Write agent metadata unification plan to .md file",
  "agent_id": "a71621bd70b0e5182",
  "agent_type": "general-purpose",
  "session_id": "38879609-c8bd-47f5-af26-6210d2de543c",
  "discord_message_id": "omni_zgqadiw9",
  "discord_user": null,
  "run_in_background": true,
  "isolation": null,
  "model": null,
  "log": [
    {
      "ts": "2026-04-07T05:14:04Z",
      "event": "started",
      "context": "Write agent metadata unification plan to .md file"
    },
    {
      "ts": "2026-04-07T05:14:59Z",
      "event": "done",
      "context": "Done. File written and pushed.\n\n**Path:** `/mnt/data/bigclungus-meta/plans/agent-metadata-unification.md`\n\nThe plan is 165 lines and covers the full arc: schema (3 tables — `agents`, `tasks`, `task_events`), 6 milestones in dependency order, a what-dies/what-stays table, risk table, and open questions. Committed to `bigclungus-meta` repo (that's where the submodule/repo lives, not the parent `/mnt/data` repo which gitignores it).",
      "artifacts": []
    }
  ]
}
