{
  "id": "task-20260327-190327-a6d8cd77",
  "title": "Clean up stale RunPod tasks",
  "agent_id": "a6d8cd778c70d53d5",
  "agent_type": "general-purpose",
  "session_id": "b8a58c15-c6f1-48c2-b033-87763f636706",
  "discord_message_id": null,
  "discord_user": null,
  "run_in_background": true,
  "isolation": null,
  "model": null,
  "log": [
    {
      "ts": "2026-03-27T19:03:27Z",
      "event": "started",
      "context": "Clean up stale RunPod tasks"
    },
    {
      "ts": "2026-03-27T19:03:00Z",
      "event": "done",
      "msg": "Pepe 70B deployed on RunPod serverless, proxy integrated"
    }
  ],
  "status": "done"
}